knowledge_graph_rag/__init__.py
knowledge_graph_rag/document.py
knowledge_graph_rag/documents_cluster.py
knowledge_graph_rag/documents_graph.py
knowledge_graph_rag/knowledge_graph.py
knowledge_graph_rag/vectordb.py
knowledge_graph_rag/utils/__init__.py
knowledge_graph_rag/utils/llm.py
knowledge_graph_rag/utils/prompts.py
knowledge_graph_rag/utils/text_preprocessing.py
knowledge_graph_rag-0.1.0.dist-info/LICENSE
knowledge_graph_rag-0.1.0.dist-info/METADATA
knowledge_graph_rag-0.1.0.dist-info/WHEEL
knowledge_graph_rag-0.1.0.dist-info/top_level.txt
knowledge_graph_rag-0.1.0.dist-info/RECORD
