Metadata-Version: 2.1
Name: knowledge-graph-rag
Version: 0.1.0
License-File: LICENSE
Requires-Dist: numpy (==1.24.0)
Requires-Dist: networkx (==3.2.1)
Requires-Dist: nltk (==3.8.1)
Requires-Dist: litellm (==1.34.0)
